<?xml version="1.0" encoding="UTF-8"?>
<PeakList>
  <PeakList1D>
    <PeakList1DHeader creator="nmr" date="2023-07-25T11:55:04.770+02:00" expNo="14" name="230725_desired" owner="" procNo="1" source="/opt/nmrdata/user/nmr/Nour">
      <PeakPickDetails>F1=14.997400ppm, F2=-4.997401ppm, MI=0.10cm, MAXI=10000.00cm, PC=1.000
      </PeakPickDetails>
    </PeakList1DHeader>
    <Peak1D F1="9.797779" intensity="5.277717e-01" type="0"/>
    <Peak1D F1="9.781740" intensity="5.300332e-01" type="0"/>
    <Peak1D F1="9.676948" intensity="4.164757e-01" type="0"/>
    <Peak1D F1="9.660668" intensity="4.117630e-01" type="0"/>
    <Peak1D F1="6.247411" intensity="8.674936e-01" type="0"/>
    <Peak1D F1="6.227144" intensity="9.044402e-01" type="0"/>
    <Peak1D F1="5.885551" intensity="3.144825e+00" type="0"/>
    <Peak1D F1="5.701517" intensity="1.262744e-01" type="0"/>
    <Peak1D F1="5.686641" intensity="2.480418e-01" type="0"/>
    <Peak1D F1="5.684323" intensity="2.726065e-01" type="0"/>
    <Peak1D F1="5.670673" intensity="1.596852e-01" type="0"/>
    <Peak1D F1="5.668353" intensity="1.561780e-01" type="0"/>
    <Peak1D F1="4.986101" intensity="1.296890e-01" type="0"/>
    <Peak1D F1="4.976308" intensity="1.452617e-01" type="0"/>
    <Peak1D F1="4.973679" intensity="2.079512e-01" type="0"/>
    <Peak1D F1="4.970737" intensity="1.247441e-01" type="0"/>
    <Peak1D F1="4.967457" intensity="1.156884e-01" type="0"/>
    <Peak1D F1="4.964139" intensity="1.848976e-01" type="0"/>
    <Peak1D F1="4.961447" intensity="2.627589e-01" type="0"/>
    <Peak1D F1="4.958488" intensity="2.535453e-01" type="0"/>
    <Peak1D F1="4.955529" intensity="2.096429e-01" type="0"/>
    <Peak1D F1="4.952548" intensity="2.187073e-01" type="0"/>
    <Peak1D F1="4.949809" intensity="3.363417e-01" type="0"/>
    <Peak1D F1="4.946970" intensity="4.316715e-01" type="0"/>
    <Peak1D F1="4.944248" intensity="3.928921e-01" type="0"/>
    <Peak1D F1="4.941521" intensity="2.822830e-01" type="0"/>
    <Peak1D F1="4.938540" intensity="1.986455e-01" type="0"/>
    <Peak1D F1="4.935386" intensity="2.056474e-01" type="0"/>
    <Peak1D F1="4.932558" intensity="2.412983e-01" type="0"/>
    <Peak1D F1="4.929836" intensity="2.137944e-01" type="0"/>
    <Peak1D F1="3.575971" intensity="1.404394e-01" type="0"/>
    <Peak1D F1="3.562527" intensity="1.694536e-01" type="0"/>
    <Peak1D F1="3.465755" intensity="6.902902e+00" type="0"/>
    <Peak1D F1="3.458073" intensity="2.312650e-01" type="0"/>
    <Peak1D F1="3.451483" intensity="1.223676e+01" type="0"/>
    <Peak1D F1="3.447809" intensity="4.505517e-01" type="0"/>
    <Peak1D F1="3.322869" intensity="3.365902e-01" type="0"/>
    <Peak1D F1="3.308774" intensity="1.012126e+00" type="0"/>
    <Peak1D F1="3.294720" intensity="9.895772e-01" type="0"/>
    <Peak1D F1="3.280713" intensity="3.133108e-01" type="0"/>
    <Peak1D F1="2.489111" intensity="2.257638e-01" type="0"/>
    <Peak1D F1="2.474391" intensity="4.718084e-01" type="0"/>
    <Peak1D F1="2.459912" intensity="2.591940e-01" type="0"/>
    <Peak1D F1="2.299330" intensity="3.746028e-01" type="0"/>
    <Peak1D F1="2.285622" intensity="7.185239e-01" type="0"/>
    <Peak1D F1="2.273002" intensity="4.643521e-01" type="0"/>
    <Peak1D F1="2.206768" intensity="5.013107e-01" type="0"/>
    <Peak1D F1="2.204402" intensity="4.864862e-01" type="0"/>
    <Peak1D F1="2.194256" intensity="8.174765e-01" type="0"/>
    <Peak1D F1="2.190367" intensity="7.363738e-01" type="0"/>
    <Peak1D F1="2.179066" intensity="6.583530e-01" type="0"/>
    <Peak1D F1="2.125531" intensity="2.492890e-01" type="0"/>
    <Peak1D F1="2.122805" intensity="2.421511e-01" type="0"/>
    <Peak1D F1="2.108336" intensity="4.239894e-01" type="0"/>
    <Peak1D F1="2.095201" intensity="4.632339e-01" type="0"/>
    <Peak1D F1="2.082484" intensity="1.581607e-01" type="0"/>
    <Peak1D F1="2.071320" intensity="1.969480e-01" type="0"/>
    <Peak1D F1="2.058480" intensity="1.224993e-01" type="0"/>
    <Peak1D F1="2.037608" intensity="1.418115e+00" type="0"/>
    <Peak1D F1="2.035054" intensity="1.363736e+00" type="0"/>
    <Peak1D F1="1.967118" intensity="1.167675e-01" type="0"/>
    <Peak1D F1="1.935102" intensity="1.928250e-01" type="0"/>
    <Peak1D F1="1.920232" intensity="4.670448e-01" type="0"/>
    <Peak1D F1="1.904137" intensity="4.770748e-01" type="0"/>
    <Peak1D F1="1.888368" intensity="2.279449e-01" type="0"/>
    <Peak1D F1="1.845033" intensity="1.538842e+00" type="0"/>
    <Peak1D F1="1.842413" intensity="1.452218e+00" type="0"/>
    <Peak1D F1="1.831103" intensity="1.629859e-01" type="0"/>
    <Peak1D F1="1.826844" intensity="1.412269e-01" type="0"/>
    <Peak1D F1="1.818692" intensity="3.651963e-01" type="0"/>
    <Peak1D F1="1.816061" intensity="3.539272e-01" type="0"/>
    <Peak1D F1="1.812485" intensity="2.447235e-01" type="0"/>
    <Peak1D F1="1.804942" intensity="4.350521e-01" type="0"/>
    <Peak1D F1="1.801242" intensity="3.529735e-01" type="0"/>
    <Peak1D F1="1.792411" intensity="2.487819e-01" type="0"/>
    <Peak1D F1="1.786658" intensity="2.154103e-01" type="0"/>
    <Peak1D F1="1.780674" intensity="1.099115e-01" type="0"/>
    <Peak1D F1="1.774310" intensity="1.678267e-01" type="0"/>
    <Peak1D F1="1.761588" intensity="1.004627e-01" type="0"/>
    <Peak1D F1="1.599583" intensity="2.143621e-01" type="0"/>
    <Peak1D F1="1.583949" intensity="3.620490e-01" type="0"/>
    <Peak1D F1="1.571401" intensity="3.308398e-01" type="0"/>
    <Peak1D F1="1.566578" intensity="2.006563e-01" type="0"/>
    <Peak1D F1="1.555894" intensity="3.418300e-01" type="0"/>
    <Peak1D F1="1.554022" intensity="3.858185e-01" type="0"/>
    <Peak1D F1="1.548405" intensity="4.046606e-01" type="0"/>
    <Peak1D F1="1.545918" intensity="3.830170e-01" type="0"/>
    <Peak1D F1="1.538422" intensity="3.131357e-01" type="0"/>
    <Peak1D F1="1.524135" intensity="9.581659e-01" type="0"/>
    <Peak1D F1="1.522045" intensity="9.538287e-01" type="0"/>
    <Peak1D F1="1.508787" intensity="3.150032e+00" type="0"/>
    <Peak1D F1="1.483913" intensity="2.904469e-01" type="0"/>
    <Peak1D F1="1.469236" intensity="4.131732e-01" type="0"/>
    <Peak1D F1="1.462836" intensity="1.038314e+00" type="0"/>
    <Peak1D F1="1.455819" intensity="3.137382e-01" type="0"/>
    <Peak1D F1="1.451336" intensity="3.366109e-01" type="0"/>
    <Peak1D F1="1.445886" intensity="3.489310e-01" type="0"/>
    <Peak1D F1="1.436059" intensity="8.405336e-01" type="0"/>
    <Peak1D F1="1.425274" intensity="2.432180e+00" type="0"/>
    <Peak1D F1="1.214662" intensity="3.573395e+00" type="0"/>
    <Peak1D F1="1.123084" intensity="1.328376e-01" type="0"/>
    <Peak1D F1="1.034599" intensity="1.716119e-01" type="0"/>
    <Peak1D F1="1.027495" intensity="6.356241e+00" type="0"/>
    <Peak1D F1="1.020659" intensity="3.295161e-01" type="0"/>
    <Peak1D F1="1.013149" intensity="5.692199e+00" type="0"/>
    <Peak1D F1="1.010793" intensity="6.673779e-01" type="0"/>
    <Peak1D F1="1.005485" intensity="4.097847e-01" type="0"/>
    <Peak1D F1="0.900933" intensity="7.453239e-01" type="0"/>
    <Peak1D F1="0.886885" intensity="1.548632e+00" type="0"/>
    <Peak1D F1="0.872812" intensity="7.436691e-01" type="0"/>
  </PeakList1D>
</PeakList>
