<?xml version="1.0" encoding="UTF-8"?>
<PeakList>
  <PeakList1D>
    <PeakList1DHeader creator="nmr" date="2023-07-21T14:21:46.747+02:00" expNo="22" name="230720_desired" owner="" procNo="1" source="/opt/nmrdata/user/nmr/Nour">
      <PeakPickDetails>F1=14.997400ppm, F2=-4.997401ppm, MI=0.10cm, MAXI=10000.00cm, PC=1.000
      </PeakPickDetails>
    </PeakList1DHeader>
    <Peak1D F1="9.795989" intensity="4.841240e-01" type="0"/>
    <Peak1D F1="9.779969" intensity="4.859118e-01" type="0"/>
    <Peak1D F1="9.675100" intensity="3.926250e-01" type="0"/>
    <Peak1D F1="9.658875" intensity="3.978661e-01" type="0"/>
    <Peak1D F1="6.245522" intensity="9.922786e-01" type="0"/>
    <Peak1D F1="6.225240" intensity="1.030272e+00" type="0"/>
    <Peak1D F1="5.883784" intensity="2.849834e+00" type="0"/>
    <Peak1D F1="5.698546" intensity="1.267817e-01" type="0"/>
    <Peak1D F1="5.684840" intensity="2.285219e-01" type="0"/>
    <Peak1D F1="5.682593" intensity="2.707259e-01" type="0"/>
    <Peak1D F1="5.668892" intensity="1.500876e-01" type="0"/>
    <Peak1D F1="5.666506" intensity="1.514723e-01" type="0"/>
    <Peak1D F1="5.151543" intensity="1.343954e-01" type="0"/>
    <Peak1D F1="5.141981" intensity="1.062221e-01" type="0"/>
    <Peak1D F1="4.984224" intensity="1.316222e-01" type="0"/>
    <Peak1D F1="4.971796" intensity="2.139995e-01" type="0"/>
    <Peak1D F1="4.968969" intensity="1.388673e-01" type="0"/>
    <Peak1D F1="4.965152" intensity="1.217987e-01" type="0"/>
    <Peak1D F1="4.962426" intensity="2.040376e-01" type="0"/>
    <Peak1D F1="4.959569" intensity="2.937579e-01" type="0"/>
    <Peak1D F1="4.956702" intensity="2.885686e-01" type="0"/>
    <Peak1D F1="4.953784" intensity="2.289811e-01" type="0"/>
    <Peak1D F1="4.950793" intensity="2.511001e-01" type="0"/>
    <Peak1D F1="4.947946" intensity="3.786394e-01" type="0"/>
    <Peak1D F1="4.945143" intensity="5.006944e-01" type="0"/>
    <Peak1D F1="4.942425" intensity="4.450472e-01" type="0"/>
    <Peak1D F1="4.939726" intensity="3.101634e-01" type="0"/>
    <Peak1D F1="4.936643" intensity="2.221172e-01" type="0"/>
    <Peak1D F1="4.933631" intensity="2.354316e-01" type="0"/>
    <Peak1D F1="4.930779" intensity="2.659063e-01" type="0"/>
    <Peak1D F1="4.927919" intensity="2.411027e-01" type="0"/>
    <Peak1D F1="3.560760" intensity="1.016535e-01" type="0"/>
    <Peak1D F1="3.462671" intensity="1.765280e+00" type="0"/>
    <Peak1D F1="3.448638" intensity="3.277887e+00" type="0"/>
    <Peak1D F1="3.320938" intensity="1.310944e-01" type="0"/>
    <Peak1D F1="3.306553" intensity="3.456071e-01" type="0"/>
    <Peak1D F1="3.292289" intensity="3.296391e-01" type="0"/>
    <Peak1D F1="3.278837" intensity="1.082066e-01" type="0"/>
    <Peak1D F1="3.173558" intensity="1.174292e-01" type="0"/>
    <Peak1D F1="2.487134" intensity="2.283661e-01" type="0"/>
    <Peak1D F1="2.472621" intensity="4.707427e-01" type="0"/>
    <Peak1D F1="2.457991" intensity="2.587685e-01" type="0"/>
    <Peak1D F1="2.296429" intensity="4.309367e-01" type="0"/>
    <Peak1D F1="2.283210" intensity="8.614868e-01" type="0"/>
    <Peak1D F1="2.270886" intensity="5.551967e-01" type="0"/>
    <Peak1D F1="2.204843" intensity="5.200453e-01" type="0"/>
    <Peak1D F1="2.202503" intensity="5.228744e-01" type="0"/>
    <Peak1D F1="2.192346" intensity="9.018171e-01" type="0"/>
    <Peak1D F1="2.188444" intensity="8.195156e-01" type="0"/>
    <Peak1D F1="2.177067" intensity="7.722499e-01" type="0"/>
    <Peak1D F1="2.120276" intensity="1.362854e-01" type="0"/>
    <Peak1D F1="2.106275" intensity="3.862989e-01" type="0"/>
    <Peak1D F1="2.093368" intensity="4.580376e-01" type="0"/>
    <Peak1D F1="2.081023" intensity="1.599646e-01" type="0"/>
    <Peak1D F1="2.069885" intensity="1.909352e-01" type="0"/>
    <Peak1D F1="2.057012" intensity="1.279760e-01" type="0"/>
    <Peak1D F1="2.035775" intensity="1.319913e+00" type="0"/>
    <Peak1D F1="2.033242" intensity="1.357286e+00" type="0"/>
    <Peak1D F1="2.022808" intensity="1.656404e-01" type="0"/>
    <Peak1D F1="1.981692" intensity="7.961342e-01" type="0"/>
    <Peak1D F1="1.964914" intensity="1.055594e-01" type="0"/>
    <Peak1D F1="1.960737" intensity="1.019830e-01" type="0"/>
    <Peak1D F1="1.933541" intensity="2.199248e-01" type="0"/>
    <Peak1D F1="1.917844" intensity="5.454719e-01" type="0"/>
    <Peak1D F1="1.901684" intensity="5.669813e-01" type="0"/>
    <Peak1D F1="1.885984" intensity="2.579354e-01" type="0"/>
    <Peak1D F1="1.843230" intensity="1.418645e+00" type="0"/>
    <Peak1D F1="1.840616" intensity="1.388023e+00" type="0"/>
    <Peak1D F1="1.829291" intensity="1.863648e-01" type="0"/>
    <Peak1D F1="1.825241" intensity="1.634533e-01" type="0"/>
    <Peak1D F1="1.816732" intensity="4.120841e-01" type="0"/>
    <Peak1D F1="1.814302" intensity="4.162317e-01" type="0"/>
    <Peak1D F1="1.810717" intensity="2.931929e-01" type="0"/>
    <Peak1D F1="1.802889" intensity="6.885812e-01" type="0"/>
    <Peak1D F1="1.799516" intensity="4.192658e-01" type="0"/>
    <Peak1D F1="1.790282" intensity="2.876438e-01" type="0"/>
    <Peak1D F1="1.784730" intensity="2.469759e-01" type="0"/>
    <Peak1D F1="1.778974" intensity="1.216820e-01" type="0"/>
    <Peak1D F1="1.772481" intensity="1.451684e-01" type="0"/>
    <Peak1D F1="1.747893" intensity="1.564766e-01" type="0"/>
    <Peak1D F1="1.745637" intensity="1.581038e-01" type="0"/>
    <Peak1D F1="1.597600" intensity="2.400635e-01" type="0"/>
    <Peak1D F1="1.582049" intensity="3.900291e-01" type="0"/>
    <Peak1D F1="1.569420" intensity="3.705622e-01" type="0"/>
    <Peak1D F1="1.564709" intensity="2.216450e-01" type="0"/>
    <Peak1D F1="1.552177" intensity="4.503746e-01" type="0"/>
    <Peak1D F1="1.546426" intensity="3.728475e-01" type="0"/>
    <Peak1D F1="1.543981" intensity="3.772771e-01" type="0"/>
    <Peak1D F1="1.536490" intensity="3.539052e-01" type="0"/>
    <Peak1D F1="1.521886" intensity="9.078655e-01" type="0"/>
    <Peak1D F1="1.520156" intensity="9.580418e-01" type="0"/>
    <Peak1D F1="1.506773" intensity="3.545270e+00" type="0"/>
    <Peak1D F1="1.482055" intensity="3.208964e-01" type="0"/>
    <Peak1D F1="1.467384" intensity="4.444193e-01" type="0"/>
    <Peak1D F1="1.459930" intensity="1.034180e+00" type="0"/>
    <Peak1D F1="1.453921" intensity="4.811553e-01" type="0"/>
    <Peak1D F1="1.449390" intensity="4.518631e-01" type="0"/>
    <Peak1D F1="1.444601" intensity="3.794101e-01" type="0"/>
    <Peak1D F1="1.433521" intensity="8.384822e-01" type="0"/>
    <Peak1D F1="1.422129" intensity="2.964628e+00" type="0"/>
    <Peak1D F1="1.212752" intensity="3.896442e+00" type="0"/>
    <Peak1D F1="1.120637" intensity="1.003644e-01" type="0"/>
    <Peak1D F1="1.025093" intensity="5.111156e+00" type="0"/>
    <Peak1D F1="1.023034" intensity="1.223109e+00" type="0"/>
    <Peak1D F1="1.017816" intensity="4.588540e-01" type="0"/>
    <Peak1D F1="1.010612" intensity="4.138829e+00" type="0"/>
    <Peak1D F1="1.008033" intensity="9.874607e-01" type="0"/>
    <Peak1D F1="1.003050" intensity="1.156783e+00" type="0"/>
    <Peak1D F1="0.988444" intensity="4.073321e-01" type="0"/>
    <Peak1D F1="0.898873" intensity="8.062481e-01" type="0"/>
    <Peak1D F1="0.884824" intensity="1.676622e+00" type="0"/>
    <Peak1D F1="0.870715" intensity="8.226167e-01" type="0"/>
  </PeakList1D>
</PeakList>
